pesto/__init__.py
pesto/version.py
pesto/cli/__init__.py
pesto/cli/app.py
pesto/cli/build.py
pesto/cli/fields.py
pesto/cli/run.py
pesto/cli/schemagen.py
pesto/cli/core/__init__.py
pesto/cli/core/build_config.py
pesto/cli/core/config_loader.py
pesto/cli/core/docker_builder.py
pesto/cli/core/pesto_files.py
pesto/cli/core/profile_loader.py
pesto/cli/core/utils.py
pesto/cli/experimental/__init__.py
pesto/cli/experimental/push.py
pesto/cli/resources/Dockerfile
pesto/cli/resources/__init__.py
pesto/cli/resources/banner.txt
pesto/cli/resources/doc/api_geo_process_v1.0.yaml
pesto/cli/resources/doc/swagger.png
pesto/cli/resources/schema/definitions.json
pesto/cli/resources/schema/requirements_schema.json
pesto/cli/resources/schema/service_schema.json
pesto/cli/resources/template/README.md
pesto/cli/resources/template/__init__.py
pesto/cli/resources/template/cookiecutter.json
pesto/cli/resources/template/{{cookiecutter.project_sname}}/MANIFEST.in
pesto/cli/resources/template/{{cookiecutter.project_sname}}/Makefile
pesto/cli/resources/template/{{cookiecutter.project_sname}}/README.md
pesto/cli/resources/template/{{cookiecutter.project_sname}}/__init__.py
pesto/cli/resources/template/{{cookiecutter.project_sname}}/requirements.txt
pesto/cli/resources/template/{{cookiecutter.project_sname}}/setup.py
pesto/cli/resources/template/{{cookiecutter.project_sname}}/algorithm/__init__.py
pesto/cli/resources/template/{{cookiecutter.project_sname}}/algorithm/input_output.py
pesto/cli/resources/template/{{cookiecutter.project_sname}}/algorithm/process.py
pesto/cli/resources/template/{{cookiecutter.project_sname}}/pesto/api/config.json
pesto/cli/resources/template/{{cookiecutter.project_sname}}/pesto/api/config_schema.json
pesto/cli/resources/template/{{cookiecutter.project_sname}}/pesto/api/description.json
pesto/cli/resources/template/{{cookiecutter.project_sname}}/pesto/api/description.stateful.json
pesto/cli/resources/template/{{cookiecutter.project_sname}}/pesto/api/input_schema.json
processing_factory-1.7.2.dist-info/METADATA
processing_factory-1.7.2.dist-info/WHEEL
processing_factory-1.7.2.dist-info/entry_points.txt
processing_factory-1.7.2.dist-info/top_level.txt
processing_factory-1.7.2.dist-info/RECORD
